LICENSE
MANIFEST.in
README.md
pyproject.toml
setup.cfg
setup.py
src/in_transformers.egg-info/PKG-INFO
src/in_transformers.egg-info/SOURCES.txt
src/in_transformers.egg-info/dependency_links.txt
src/in_transformers.egg-info/entry_points.txt
src/in_transformers.egg-info/not-zip-safe
src/in_transformers.egg-info/requires.txt
src/in_transformers.egg-info/top_level.txt
src/transformers/__init__.py
src/transformers/activations.py
src/transformers/activations_tf.py
src/transformers/configuration_utils.py
src/transformers/convert_graph_to_onnx.py
src/transformers/convert_pytorch_checkpoint_to_tf2.py
src/transformers/convert_slow_tokenizer.py
src/transformers/convert_slow_tokenizers_checkpoints_to_fast.py
src/transformers/convert_tf_hub_seq_to_seq_bert_to_pytorch.py
src/transformers/debug_utils.py
src/transformers/deepspeed.py
src/transformers/dependency_versions_check.py
src/transformers/dependency_versions_table.py
src/transformers/dynamic_module_utils.py
src/transformers/feature_extraction_sequence_utils.py
src/transformers/feature_extraction_utils.py
src/transformers/file_utils.py
src/transformers/generation_flax_utils.py
src/transformers/generation_tf_utils.py
src/transformers/generation_utils.py
src/transformers/hf_argparser.py
src/transformers/image_processing_utils.py
src/transformers/image_transforms.py
src/transformers/image_utils.py
src/transformers/integrations.py
src/transformers/keras_callbacks.py
src/transformers/modelcard.py
src/transformers/modeling_flax_outputs.py
src/transformers/modeling_flax_pytorch_utils.py
src/transformers/modeling_flax_utils.py
src/transformers/modeling_outputs.py
src/transformers/modeling_tf_outputs.py
src/transformers/modeling_tf_pytorch_utils.py
src/transformers/modeling_tf_utils.py
src/transformers/modeling_utils.py
src/transformers/optimization.py
src/transformers/optimization_tf.py
src/transformers/processing_utils.py
src/transformers/pytorch_utils.py
src/transformers/testing_utils.py
src/transformers/tf_utils.py
src/transformers/tokenization_utils.py
src/transformers/tokenization_utils_base.py
src/transformers/tokenization_utils_fast.py
src/transformers/trainer.py
src/transformers/trainer_callback.py
src/transformers/trainer_pt_utils.py
src/transformers/trainer_seq2seq.py
src/transformers/trainer_tf.py
