Metadata-Version: 2.1
Name: in-transformers
Version: 1.0.0
Summary: State-of-the-art Machine Learning for JAX, PyTorch and TensorFlow
Home-page: https://github.com/huggingface/transformers
Author: The Hugging Face team (past and future) with the help of all our contributors (https://github.com/huggingface/transformers/graphs/contributors)
Author-email: transformers@huggingface.co
License: Apache
Keywords: NLP vision speech deep learning transformer pytorch tensorflow BERT GPT-2 Wav2Vec2 ViT
Platform: UNKNOWN
Classifier: Development Status :: 5 - Production/Stable
Classifier: Intended Audience :: Developers
Classifier: Intended Audience :: Education
Classifier: Intended Audience :: Science/Research
Classifier: License :: OSI Approved :: Apache Software License
Classifier: Operating System :: OS Independent
Classifier: Programming Language :: Python :: 3
Classifier: Programming Language :: Python :: 3.7
Classifier: Programming Language :: Python :: 3.8
Classifier: Programming Language :: Python :: 3.9
Classifier: Topic :: Scientific/Engineering :: Artificial Intelligence
Requires-Python: >=3.7.0
Provides-Extra: ja
Provides-Extra: sklearn
Provides-Extra: tf
Provides-Extra: tf-cpu
Provides-Extra: torch
Provides-Extra: accelerate
Provides-Extra: retrieval
Provides-Extra: flax
Provides-Extra: tokenizers
Provides-Extra: ftfy
Provides-Extra: onnxruntime
Provides-Extra: onnx
Provides-Extra: modelcreation
Provides-Extra: sagemaker
Provides-Extra: deepspeed
Provides-Extra: fairscale
Provides-Extra: optuna
Provides-Extra: ray
Provides-Extra: sigopt
Provides-Extra: integrations
Provides-Extra: serving
Provides-Extra: audio
Provides-Extra: speech
Provides-Extra: torch-speech
Provides-Extra: tf-speech
Provides-Extra: flax-speech
Provides-Extra: vision
Provides-Extra: timm
Provides-Extra: natten
Provides-Extra: codecarbon
Provides-Extra: video
Provides-Extra: sentencepiece
Provides-Extra: testing
Provides-Extra: deepspeed-testing
Provides-Extra: quality
Provides-Extra: all
Provides-Extra: docs_specific
Provides-Extra: docs
Provides-Extra: dev-torch
Provides-Extra: dev-tensorflow
Provides-Extra: dev
Provides-Extra: torchhub
License-File: LICENSE
